stance_llm/__init__.py
stance_llm/base.py
stance_llm/process.py
stance_llm-0.3.0.dist-info/licenses/LICENSE
stance_llm-0.3.0.dist-info/METADATA
stance_llm-0.3.0.dist-info/WHEEL
stance_llm-0.3.0.dist-info/top_level.txt
stance_llm-0.3.0.dist-info/RECORD
