Metadata-Version: 2.4
Name: stance-llm
Version: 0.3.0
Summary: Classify stances of entities related to a statement in German or English text using large language models (LLMs)
Author-email: Mario Angst <mario.angst@uzh.ch>, Viviane Walker <viviane.walker@uzh.ch>
License-Expression: MIT
Project-URL: repository, https://github.com/urban-sustainability-lab-zurich/stance-llm
Requires-Python: >=3.12
License-File: LICENSE
Requires-Dist: guidance>=0.2.0
Requires-Dist: loguru>=0.7.2
Requires-Dist: tqdm>=4.65.0
Requires-Dist: polars>=0.20.15
Requires-Dist: wonderwords>=2.2.0
Requires-Dist: scikit-learn>=1.4.2
Requires-Dist: numpy==1.26.4
Dynamic: license-file
